scheduler/__init__.py
scheduler/scheduler.py
uottawa_scheduler/__init__.py
uottawa_scheduler/scheduler.py
uottawa_gym_scheduler-0.0.3.dist-info/LICENSE
uottawa_gym_scheduler-0.0.3.dist-info/METADATA
uottawa_gym_scheduler-0.0.3.dist-info/WHEEL
uottawa_gym_scheduler-0.0.3.dist-info/entry_points.txt
uottawa_gym_scheduler-0.0.3.dist-info/top_level.txt
uottawa_gym_scheduler-0.0.3.dist-info/RECORD
