Metadata-Version: 2.1
Name: uottawa-gym-scheduler
Version: 0.0.3
Summary: uOttawa COVID Gym Scheduler
Home-page: https://github.com/photonized/uOttawa-Gym-Scheduler
Author: Vladislav Jidkov
Author-email: vladjdk@gmail.com
License: UNKNOWN
Platform: UNKNOWN
Classifier: Programming Language :: Python :: 3
Classifier: License :: OSI Approved :: Apache Software License
Classifier: Operating System :: OS Independent
Requires-Python: >=3.6
Requires-Dist: pandas
Requires-Dist: beautifulsoup4
Requires-Dist: requests
